ook/__init__.py
ook/_version.py
ook/decorators.py
ook/util.py
ook-1.0.2.dist-info/DESCRIPTION.rst
ook-1.0.2.dist-info/METADATA
ook-1.0.2.dist-info/RECORD
ook-1.0.2.dist-info/WHEEL
ook-1.0.2.dist-info/metadata.json
ook-1.0.2.dist-info/top_level.txt
